preen/__init__.py
preen/__main__.py
preen/cli.py
preen/config.py
preen/interactive.py
preen/syncer.py
preen/checks/__init__.py
preen/checks/base.py
preen/checks/ci_matrix.py
preen/checks/citation.py
preen/checks/codespell.py
preen/checks/deps.py
preen/checks/deptree.py
preen/checks/links.py
preen/checks/pydoclint.py
preen/checks/pyright.py
preen/checks/ruff.py
preen/checks/runner.py
preen/checks/structure.py
preen/checks/tests.py
preen/checks/version.py
preen/commands/__init__.py
preen/commands/bump.py
preen/commands/fix.py
preen/commands/init.py
preen/commands/release.py
preen/templates/__init__.py
preen/templates/manager.py
preen-0.1.0.dist-info/licenses/LICENSE
preen-0.1.0.dist-info/METADATA
preen-0.1.0.dist-info/WHEEL
preen-0.1.0.dist-info/entry_points.txt
preen-0.1.0.dist-info/top_level.txt
preen-0.1.0.dist-info/RECORD
