Metadata-Version: 2.4
Name: preen
Version: 0.1.0
Summary: An opinionated, agentic CLI for Python package hygiene and release
Author-email: Gaurav Sood <contact@gsood.com>
License: MIT
Project-URL: Homepage, https://github.com/gojiplus/preen
Project-URL: Repository, https://github.com/gojiplus/preen
Project-URL: Documentation, https://gojiplus.github.io/preen
Project-URL: Bug Tracker, https://github.com/gojiplus/preen/issues
Project-URL: Changelog, https://github.com/gojiplus/preen/releases
Keywords: packaging,release,metadata,hygiene,cli,python
Classifier: Programming Language :: Python :: 3
Classifier: Programming Language :: Python :: 3 :: Only
Classifier: Programming Language :: Python :: 3.12
Classifier: Programming Language :: Python :: 3.13
Classifier: Programming Language :: Python :: 3.14
Classifier: License :: OSI Approved :: MIT License
Classifier: Development Status :: 3 - Alpha
Classifier: Intended Audience :: Developers
Classifier: Topic :: Software Development :: Build Tools
Classifier: Topic :: Software Development :: Libraries :: Python Modules
Requires-Python: >=3.12
License-File: LICENSE
Requires-Dist: typer>=0.9
Requires-Dist: rich>=13.5
Requires-Dist: PyYAML>=6.0
Requires-Dist: Jinja2>=3.0
Requires-Dist: httpx>=0.24.0
Requires-Dist: pydoclint>=0.3.0
Requires-Dist: pyright>=1.1.350
Requires-Dist: codespell>=2.3.0
Requires-Dist: ruff>=0.14.0
Provides-Extra: dev
Requires-Dist: pytest>=7.0; extra == "dev"
Requires-Dist: pytest-cov; extra == "dev"
Provides-Extra: docs
Requires-Dist: sphinx>=7.0; extra == "docs"
Requires-Dist: sphinx-rtd-theme>=2.0; extra == "docs"
Requires-Dist: myst-parser>=2.0; extra == "docs"
Requires-Dist: furo>=2024.0; extra == "docs"
Dynamic: license-file
